[
  { "name": "Smartphone Dual Chip", "category": "Eletrônicos", "unsplashQuery": "smartphone" },
  { "name": "Fone de Ouvido Bluetooth TWS", "category": "Eletrônicos", "unsplashQuery": "wireless earbuds" },
  { "name": "Carregador Turbo USB-C 20W", "category": "Eletrônicos", "unsplashQuery": "phone charger" },
  { "name": "Power Bank 10000mAh", "category": "Eletrônicos", "unsplashQuery": "power bank" },
  { "name": "Caixa de Som Bluetooth Portátil", "category": "Eletrônicos", "unsplashQuery": "bluetooth speaker" },
  { "name": "Smartwatch Esportivo", "category": "Eletrônicos", "unsplashQuery": "smartwatch" },
  { "name": "Cabo USB-C Reforçado", "category": "Eletrônicos", "unsplashQuery": "usb cable" },
  { "name": "Mouse Sem Fio", "category": "Eletrônicos", "unsplashQuery": "wireless mouse" },
  { "name": "Teclado Bluetooth", "category": "Eletrônicos", "unsplashQuery": "bluetooth keyboard" },
  { "name": "Câmera de Segurança Wi-Fi", "category": "Eletrônicos", "unsplashQuery": "security camera" },
  { "name": "Drone com Câmera", "category": "Eletrônicos", "unsplashQuery": "drone camera" },
  { "name": "Tablet 10 Polegadas", "category": "Eletrônicos", "unsplashQuery": "tablet device" },

  { "name": "Perfume Importado Masculino 100ml", "category": "Perfumaria", "unsplashQuery": "men perfume bottle" },
  { "name": "Perfume Importado Feminino 100ml", "category": "Perfumaria", "unsplashQuery": "women perfume bottle" },
  { "name": "Kit Miniaturas de Perfume", "category": "Perfumaria", "unsplashQuery": "perfume miniature set" },
  { "name": "Body Splash Importado", "category": "Perfumaria", "unsplashQuery": "body splash bottle" },
  { "name": "Desodorante Colônia Importado", "category": "Perfumaria", "unsplashQuery": "cologne bottle" },
  { "name": "Perfume Árabe Importado", "category": "Perfumaria", "unsplashQuery": "arabian perfume bottle" },
  { "name": "Loção Hidratante Perfumada", "category": "Perfumaria", "unsplashQuery": "body lotion bottle" },
  { "name": "Sabonete Líquido Perfumado", "category": "Perfumaria", "unsplashQuery": "liquid soap bottle" },
  { "name": "Difusor de Ambiente Importado", "category": "Perfumaria", "unsplashQuery": "reed diffuser" },
  { "name": "Perfume Infantil", "category": "Perfumaria", "unsplashQuery": "kids perfume bottle" },
  { "name": "Água de Cheiro Importada", "category": "Perfumaria", "unsplashQuery": "eau de cologne" },
  { "name": "Vela Aromática Importada", "category": "Perfumaria", "unsplashQuery": "scented candle" },

  { "name": "Boneca de Vinil", "category": "Brinquedos", "unsplashQuery": "vinyl doll toy" },
  { "name": "Carrinho de Controle Remoto", "category": "Brinquedos", "unsplashQuery": "remote control car" },
  { "name": "Pelúcia Personagem", "category": "Brinquedos", "unsplashQuery": "plush toy" },
  { "name": "Quebra-Cabeça 500 Peças", "category": "Brinquedos", "unsplashQuery": "jigsaw puzzle" },
  { "name": "Boneco de Ação", "category": "Brinquedos", "unsplashQuery": "action figure toy" },
  { "name": "Blocos de Montar Compatível", "category": "Brinquedos", "unsplashQuery": "building blocks toy" },
  { "name": "Patinete Infantil", "category": "Brinquedos", "unsplashQuery": "kids scooter" },
  { "name": "Bicicleta Infantil Aro 16", "category": "Brinquedos", "unsplashQuery": "kids bicycle" },
  { "name": "Pista de Carrinhos", "category": "Brinquedos", "unsplashQuery": "toy car track" },
  { "name": "Massinha de Modelar Kit", "category": "Brinquedos", "unsplashQuery": "modeling clay kit" },
  { "name": "Bola de Futebol Infantil", "category": "Brinquedos", "unsplashQuery": "soccer ball" },
  { "name": "Jogo de Tabuleiro", "category": "Brinquedos", "unsplashQuery": "board game" },

  { "name": "Camiseta Básica Unissex", "category": "Roupas", "unsplashQuery": "plain t-shirt" },
  { "name": "Vestido Feminino Importado", "category": "Roupas", "unsplashQuery": "women dress" },
  { "name": "Calça Jeans Masculina", "category": "Roupas", "unsplashQuery": "men jeans" },
  { "name": "Conjunto Infantil", "category": "Roupas", "unsplashQuery": "kids clothing set" },
  { "name": "Jaqueta Corta-Vento", "category": "Roupas", "unsplashQuery": "windbreaker jacket" },
  { "name": "Blusa de Frio Feminina", "category": "Roupas", "unsplashQuery": "women sweater" },
  { "name": "Short Esportivo", "category": "Roupas", "unsplashQuery": "sport shorts" },
  { "name": "Camisa Polo Masculina", "category": "Roupas", "unsplashQuery": "men polo shirt" },
  { "name": "Body para Bebê", "category": "Roupas", "unsplashQuery": "baby bodysuit" },
  { "name": "Pijama Infantil", "category": "Roupas", "unsplashQuery": "kids pajamas" },
  { "name": "Macacão Feminino", "category": "Roupas", "unsplashQuery": "women jumpsuit" },
  { "name": "Bermuda Jeans", "category": "Roupas", "unsplashQuery": "denim shorts" },

  { "name": "Tênis Esportivo Masculino", "category": "Calçados", "unsplashQuery": "men sneakers" },
  { "name": "Tênis Esportivo Feminino", "category": "Calçados", "unsplashQuery": "women sneakers" },
  { "name": "Chinelo de Dedo", "category": "Calçados", "unsplashQuery": "flip flops" },
  { "name": "Sandália Feminina", "category": "Calçados", "unsplashQuery": "women sandals" },
  { "name": "Bota Coturno", "category": "Calçados", "unsplashQuery": "combat boots" },
  { "name": "Sapatênis Masculino", "category": "Calçados", "unsplashQuery": "men casual shoes" },
  { "name": "Sapato Social", "category": "Calçados", "unsplashQuery": "dress shoes" },
  { "name": "Tênis Infantil", "category": "Calçados", "unsplashQuery": "kids sneakers" },
  { "name": "Chuteira de Futsal", "category": "Calçados", "unsplashQuery": "futsal shoes" },
  { "name": "Sandália Infantil", "category": "Calçados", "unsplashQuery": "kids sandals" },
  { "name": "Slide Importado", "category": "Calçados", "unsplashQuery": "slide sandals" },
  { "name": "Tênis Cano Alto", "category": "Calçados", "unsplashQuery": "high top sneakers" },

  { "name": "Chocolate Importado", "category": "Alimentos", "unsplashQuery": "chocolate bar" },
  { "name": "Biscoito Importado", "category": "Alimentos", "unsplashQuery": "cookies package" },
  { "name": "Bala e Doces Importados", "category": "Alimentos", "unsplashQuery": "candy assortment" },
  { "name": "Achocolatado em Pó", "category": "Alimentos", "unsplashQuery": "chocolate powder" },
  { "name": "Macarrão Instantâneo Importado", "category": "Alimentos", "unsplashQuery": "instant noodles" },
  { "name": "Café Gourmet Importado", "category": "Alimentos", "unsplashQuery": "coffee beans bag" },
  { "name": "Azeite de Oliva Importado", "category": "Alimentos", "unsplashQuery": "olive oil bottle" },
  { "name": "Molho de Tomate Importado", "category": "Alimentos", "unsplashQuery": "tomato sauce jar" },
  { "name": "Cereal Matinal Importado", "category": "Alimentos", "unsplashQuery": "cereal box" },
  { "name": "Geleia Importada", "category": "Alimentos", "unsplashQuery": "jam jar" },
  { "name": "Snack Salgadinho Importado", "category": "Alimentos", "unsplashQuery": "potato chips bag" },
  { "name": "Mel Importado", "category": "Alimentos", "unsplashQuery": "honey jar" },

  { "name": "Energético Importado", "category": "Bebidas", "unsplashQuery": "energy drink can" },
  { "name": "Refrigerante Importado", "category": "Bebidas", "unsplashQuery": "soda can" },
  { "name": "Suco Importado em Lata", "category": "Bebidas", "unsplashQuery": "juice can" },
  { "name": "Cerveja Importada", "category": "Bebidas", "unsplashQuery": "imported beer bottle" },
  { "name": "Água Tônica Importada", "category": "Bebidas", "unsplashQuery": "tonic water bottle" },
  { "name": "Chá Gelado Importado", "category": "Bebidas", "unsplashQuery": "iced tea bottle" },
  { "name": "Bebida Isotônica", "category": "Bebidas", "unsplashQuery": "sports drink bottle" },
  { "name": "Whisky Importado", "category": "Bebidas", "unsplashQuery": "whisky bottle" },
  { "name": "Vinho Importado", "category": "Bebidas", "unsplashQuery": "wine bottle" },
  { "name": "Achocolatado Pronto", "category": "Bebidas", "unsplashQuery": "chocolate milk bottle" },
  { "name": "Água com Gás Importada", "category": "Bebidas", "unsplashQuery": "sparkling water bottle" },
  { "name": "Refrigerante Diet Importado", "category": "Bebidas", "unsplashQuery": "diet soda can" },

  { "name": "Detergente Concentrado Importado", "category": "Limpeza", "unsplashQuery": "dish soap bottle" },
  { "name": "Amaciante de Roupas Importado", "category": "Limpeza", "unsplashQuery": "fabric softener bottle" },
  { "name": "Multiuso Importado", "category": "Limpeza", "unsplashQuery": "all purpose cleaner spray" },
  { "name": "Desinfetante Importado", "category": "Limpeza", "unsplashQuery": "disinfectant bottle" },
  { "name": "Sabão em Barra Importado", "category": "Limpeza", "unsplashQuery": "laundry soap bar" },
  { "name": "Esponja de Limpeza Kit", "category": "Limpeza", "unsplashQuery": "cleaning sponge" },
  { "name": "Limpa Vidros Importado", "category": "Limpeza", "unsplashQuery": "glass cleaner spray" },
  { "name": "Álcool em Gel Importado", "category": "Limpeza", "unsplashQuery": "hand sanitizer gel" },
  { "name": "Saco de Lixo Reforçado", "category": "Limpeza", "unsplashQuery": "trash bags roll" },
  { "name": "Pastilha Sanitária", "category": "Limpeza", "unsplashQuery": "toilet cleaner tablet" },
  { "name": "Lustra Móveis Importado", "category": "Limpeza", "unsplashQuery": "furniture polish spray" },
  { "name": "Tira Manchas Importado", "category": "Limpeza", "unsplashQuery": "stain remover bottle" },

  { "name": "Shampoo Importado", "category": "Higiene", "unsplashQuery": "shampoo bottle" },
  { "name": "Condicionador Importado", "category": "Higiene", "unsplashQuery": "conditioner bottle" },
  { "name": "Sabonete Importado Kit", "category": "Higiene", "unsplashQuery": "soap bar set" },
  { "name": "Creme Dental Importado", "category": "Higiene", "unsplashQuery": "toothpaste tube" },
  { "name": "Escova de Dentes Elétrica", "category": "Higiene", "unsplashQuery": "electric toothbrush" },
  { "name": "Fio Dental Importado", "category": "Higiene", "unsplashQuery": "dental floss" },
  { "name": "Absorvente Importado", "category": "Higiene", "unsplashQuery": "feminine care product" },
  { "name": "Lâmina de Barbear Importada", "category": "Higiene", "unsplashQuery": "razor blade" },
  { "name": "Creme Hidratante Corporal", "category": "Higiene", "unsplashQuery": "body moisturizer cream" },
  { "name": "Protetor Solar Importado", "category": "Higiene", "unsplashQuery": "sunscreen bottle" },
  { "name": "Cotonete Importado", "category": "Higiene", "unsplashQuery": "cotton swabs" },
  { "name": "Lenço Umedecido Importado", "category": "Higiene", "unsplashQuery": "wet wipes package" }
]
